yeep/__init__.py
yeep/database.py
yeep/table.py
yeep-0.1.4.dist-info/METADATA
yeep-0.1.4.dist-info/WHEEL
yeep-0.1.4.dist-info/top_level.txt
yeep-0.1.4.dist-info/RECORD
