Metadata-Version: 2.1
Name: yeep
Version: 0.1.4
Summary: Простая и мощная библиотека для работы с PostgreSQL
Home-page: https://github.com/Timok277/yeep
Author: Tima Yeep
Author-email: timik277@gmail.com
License: UNKNOWN
Keywords: postgresql database orm sql
Platform: UNKNOWN
Classifier: Development Status :: 3 - Alpha
Classifier: Intended Audience :: Developers
Classifier: License :: OSI Approved :: MIT License
Classifier: Programming Language :: Python :: 3
Classifier: Programming Language :: Python :: 3.7
Classifier: Programming Language :: Python :: 3.8
Classifier: Programming Language :: Python :: 3.9
Classifier: Programming Language :: Python :: 3.10
Classifier: Topic :: Database
Classifier: Topic :: Software Development :: Libraries :: Python Modules
Requires-Python: >=3.7
Requires-Dist: psycopg2-binary>=2.9.0
Requires-Dist: python-dotenv>=0.19.0
